napari_console/__init__.py
napari_console/_hookimpl.py
napari_console/_version.py
napari_console/napari.yaml
napari_console/qt_console.py
napari_console/_tests/__init__.py
napari_console/_tests/test_qt_console.py
napari_console-0.1.2.dist-info/LICENSE
napari_console-0.1.2.dist-info/METADATA
napari_console-0.1.2.dist-info/WHEEL
napari_console-0.1.2.dist-info/entry_points.txt
napari_console-0.1.2.dist-info/top_level.txt
napari_console-0.1.2.dist-info/RECORD
