Metadata-Version: 2.1
Name: napari-console
Version: 0.1.2
Summary: A plugin that adds a console to napari
Author-email: napari team <napari-steering-council@googlegroups.com>
License: BSD-3-Clause
Project-URL: Homepage, https://github.com/napari/napari-console
Project-URL: Bug Tracker, https://github.com/napari/napari-console/issues
Project-URL: Source Code, https://github.com/napari/napari-console
Classifier: Development Status :: 4 - Beta
Classifier: Framework :: napari
Classifier: Intended Audience :: Developers
Classifier: License :: OSI Approved :: BSD License
Classifier: Operating System :: OS Independent
Classifier: Programming Language :: Python
Classifier: Programming Language :: Python :: 3
Classifier: Programming Language :: Python :: 3 :: Only
Classifier: Programming Language :: Python :: 3.8
Classifier: Programming Language :: Python :: 3.9
Classifier: Programming Language :: Python :: 3.10
Classifier: Programming Language :: Python :: 3.11
Classifier: Programming Language :: Python :: 3.12
Classifier: Topic :: Software Development :: Testing
Requires-Python: >=3.9
License-File: LICENSE
Requires-Dist: IPython>=7.7.0
Requires-Dist: ipykernel>=5.2.0
Requires-Dist: qtconsole!=4.7.6,!=5.4.2,>=4.5.1
Requires-Dist: qtpy>=1.7.0
Provides-Extra: pyside2
Requires-Dist: PySide2!=5.15.0,>=5.13.2; (python_version < "3.11" and platform_machine != "arm64") and extra == "pyside2"
Provides-Extra: pyside6-experimental
Requires-Dist: PySide6<6.5; python_version < "3.12" and extra == "pyside6-experimental"
Provides-Extra: pyqt6
Requires-Dist: PyQt6>6.5; extra == "pyqt6"
Requires-Dist: PyQt6!=6.6.1; platform_system == "Darwin" and extra == "pyqt6"
Provides-Extra: pyside
Requires-Dist: napari-console[pyside2]; extra == "pyside"
Provides-Extra: pyqt5
Requires-Dist: PyQt5!=5.15.0,>=5.13.2; extra == "pyqt5"
Provides-Extra: pyqt
Requires-Dist: napari-console[pyqt5]; extra == "pyqt"
Provides-Extra: qt
Requires-Dist: napari-console[pyqt]; extra == "qt"
Provides-Extra: testing
Requires-Dist: napari[pyqt]; extra == "testing"
